CHANGES.txt
LICENSE.txt
README.txt
setup.py
version.txt
raisin/__init__.py
raisin.recipe.dashboard.egg-info/PKG-INFO
raisin.recipe.dashboard.egg-info/SOURCES.txt
raisin.recipe.dashboard.egg-info/dependency_links.txt
raisin.recipe.dashboard.egg-info/entry_points.txt
raisin.recipe.dashboard.egg-info/namespace_packages.txt
raisin.recipe.dashboard.egg-info/not-zip-safe
raisin.recipe.dashboard.egg-info/requires.txt
raisin.recipe.dashboard.egg-info/top_level.txt
raisin/recipe/__init__.py
raisin/recipe/dashboard/__init__.py
raisin/recipe/dashboard/cube.py
raisin/recipe/dashboard/dashboard.py
raisin/recipe/dashboard/dashboard.py_old
raisin/recipe/dashboard/database.py_obsolete
raisin/recipe/dashboard/main.py
raisin/recipe/dashboard/renderer.py
raisin/recipe/dashboard/table.py
raisin/recipe/dashboard/tests/README.txt
raisin/recipe/dashboard/tests/__init__.py
raisin/recipe/dashboard/tests/test_cube.py
raisin/recipe/dashboard/tests/test_dashboard.py
raisin/recipe/dashboard/tests/static/index.html
raisin/recipe/dashboard/tests/static/template.html
raisin/recipe/dashboard/tests/workspace/database.csv
raisin/recipe/dashboard/tests/workspace/database.db